neural3d/__init__.py
neural3d/__main__.py
neural3d/neural3d.py
neural3d-0.1.1.dist-info/METADATA
neural3d-0.1.1.dist-info/WHEEL
neural3d-0.1.1.dist-info/licenses/LICENSE
neural3d-0.1.1.dist-info/RECORD
