Metadata-Version: 2.1
Name: neural3d
Version: 0.1.1
Summary: Unofficial API for neural3d.xyz
Project-URL: Homepage, https://github.com/neverix/neural3d
Project-URL: Bug Tracker, https://github.com/neverix/neural3d/issues
Author-email: nev <nev@neverix.io>
License:                     GNU AFFERO GENERAL PUBLIC LICENSE
Classifier: License :: OSI Approved :: MIT License
Classifier: Operating System :: OS Independent
Classifier: Programming Language :: Python :: 3
Requires-Python: >=3.7
Requires-Dist: requests
